matrice_data_processing/__init__.py
matrice_data_processing/__init__.pyi
matrice_data_processing/aug_server.cpython-312-x86_64-linux-gnu.so
matrice_data_processing/aug_server.pyi
matrice_data_processing/aug_server_v2.cpython-312-x86_64-linux-gnu.so
matrice_data_processing/aug_server_v2.pyi
matrice_data_processing/client.cpython-312-x86_64-linux-gnu.so
matrice_data_processing/client.pyi
matrice_data_processing/client_utils.cpython-312-x86_64-linux-gnu.so
matrice_data_processing/client_utils.pyi
matrice_data_processing/create_dataset.cpython-312-x86_64-linux-gnu.so
matrice_data_processing/create_dataset.pyi
matrice_data_processing/data_augmentation.cpython-312-x86_64-linux-gnu.so
matrice_data_processing/data_augmentation.pyi
matrice_data_processing/data_augmentor.cpython-312-x86_64-linux-gnu.so
matrice_data_processing/data_augmentor.pyi
matrice_data_processing/data_labelling.cpython-312-x86_64-linux-gnu.so
matrice_data_processing/data_labelling.pyi
matrice_data_processing/data_prep.cpython-312-x86_64-linux-gnu.so
matrice_data_processing/data_prep.pyi
matrice_data_processing/data_processor.cpython-312-x86_64-linux-gnu.so
matrice_data_processing/data_processor.pyi
matrice_data_processing/image_augmentations.cpython-312-x86_64-linux-gnu.so
matrice_data_processing/image_augmentations.pyi
matrice_data_processing/image_data_augmentation.cpython-312-x86_64-linux-gnu.so
matrice_data_processing/image_data_augmentation.pyi
matrice_data_processing/new_data_augmentation.cpython-312-x86_64-linux-gnu.so
matrice_data_processing/new_data_augmentation.pyi
matrice_data_processing/pipeline.cpython-312-x86_64-linux-gnu.so
matrice_data_processing/pipeline.pyi
matrice_data_processing/py.typed
matrice_data_processing/server.cpython-312-x86_64-linux-gnu.so
matrice_data_processing/server.pyi
matrice_data_processing/server_utils.cpython-312-x86_64-linux-gnu.so
matrice_data_processing/server_utils.pyi
matrice_data_processing/video_server.cpython-312-x86_64-linux-gnu.so
matrice_data_processing-0.1.1.dist-info/licenses/LICENSE.txt
matrice_data_processing-0.1.1.dist-info/METADATA
matrice_data_processing-0.1.1.dist-info/WHEEL
matrice_data_processing-0.1.1.dist-info/top_level.txt
matrice_data_processing-0.1.1.dist-info/RECORD
